test_wf68k30l_poweron.v
// WF68K30L Power-On Sequence Testbench
// Comprehensive simulation to identify startup failure causes
// Tests the critical MC68030 power-on sequence with fixed bus protocol

`timescale 1ns/1ps

module test_wf68k30l_poweron();

    // Basic test signals
    reg clk = 0;
    reg reset = 1;
    reg [2:0] cpucfg = 3'b100;     // WF68K30L selected (cpucfg[2] = 1)
    reg [2:0] cachecfg = 3'b000;   // No cache optimizations for testing
    reg [2:0] chip_ipl = 3'b111;   // No interrupts during startup

    // Clock generation - 50MHz system clock
    always #10 clk = ~clk;

    // Memory model for reset vector area (0x00000000 - 0x0000001F)
    reg [31:0] reset_memory [0:7];

    // CPU interface signals (from cpu_wrapper.v)
    wire [31:0] cpu_addr_w;
    wire [31:0] cpu_dout_w;
    reg  [31:0] cpu_din;
    wire [1:0]  size_w;
    wire        as_w;
    wire        wr_w;
    wire        ds_w;
    wire        rmc_w;
    wire [2:0]  fc_w;
    wire        reset_out_w;

    // Bus protocol signals
    wire [1:0]  dsack_w;
    wire        uds_w;
    wire        lds_w;
    wire        longword_w;
    wire [1:0]  cpustate_w;

    // Memory access control
    reg         dtack_active = 0;
    reg         mem_access_pending = 0;
    reg [3:0]   access_delay_counter = 0;

    // Test control
    integer     cycle_count = 0;
    integer     reset_vector_fetches = 0;
    reg         test_passed = 0;
    reg         test_failed = 0;

    //=================================================================
    // Extract WF68K30L bus conversion logic from cpu_wrapper.v
    //=================================================================

    // FIXED DSACK generation for WF68K30L (with corrected SIZE handling)
    // DSACK encoding: 11=no acknowledge, 10=8-bit, 01=16-bit, 00=32-bit
    // SIZE encoding: 00=byte, 01=word, 10=3-byte, 11=longword
    assign dsack_w = dtack_active ? (
        (size_w == 2'b00) ? 2'b10 :   // Byte -> 8-bit port
        (size_w == 2'b01) ? 2'b01 :   // Word -> 16-bit port
        (size_w == 2'b11) ? 2'b00 :   // Longword -> 32-bit port (FIXED!)
        2'b11                         // 3-byte/invalid -> no acknowledge
    ) : 2'b11;

    // FIXED SIZE to UDS/LDS conversion (with corrected longword detection)
    wire [1:0] byte_lanes = cpu_addr_w[1:0];
    assign uds_w = (size_w == 2'b00) ? ~(byte_lanes == 2'b00 || byte_lanes == 2'b01) :  // Byte: UDS for upper bytes
                   (size_w == 2'b01) ? ~cpu_addr_w[1] :                                   // Word: UDS based on alignment
                   (size_w == 2'b11) ? 1'b0 :                                            // Longword: both active (FIXED!)
                   1'b1;                                                                 // Reserved/3-byte

    assign lds_w = (size_w == 2'b00) ? ~(byte_lanes == 2'b10 || byte_lanes == 2'b11) :  // Byte: LDS for lower bytes
                   (size_w == 2'b01) ? ~cpu_addr_w[1] :                                   // Word: LDS based on alignment
                   (size_w == 2'b11) ? 1'b0 :                                            // Longword: both active (FIXED!)
                   1'b1;                                                                 // Reserved/3-byte

    // Map WF68K30L bus state to cpustate (invert AS since WF68K30L uses active low)
    assign cpustate_w = as_w ? 2'b01 : (~wr_w ? 2'b11 : 2'b10);
    assign longword_w = (size_w == 2'b11);  // FIXED: was 2'b10

    //=================================================================
    // Mock WF68K30L CPU Core - Behavioral Model
    //=================================================================

    reg [31:0] mock_addr;
    reg [1:0]  mock_size;
    reg        mock_as;
    reg        mock_rw;
    reg        mock_ds;
    reg        mock_rmc;
    reg [2:0]  mock_fc;
    reg [31:0] mock_dout;
    reg        mock_reset_out;

    // State machine for MC68030 startup sequence
    reg [3:0] cpu_state;
    parameter
        CPU_RESET       = 4'h0,
        CPU_FETCH_SSP_H = 4'h1,  // Fetch high word of initial SSP from 0x000000
        CPU_FETCH_SSP_L = 4'h2,  // Fetch low word of initial SSP from 0x000002
        CPU_FETCH_PC_H  = 4'h3,  // Fetch high word of initial PC from 0x000004
        CPU_FETCH_PC_L  = 4'h4,  // Fetch low word of initial PC from 0x000006
        CPU_RUNNING     = 4'h5,  // Normal operation
        CPU_FAILED      = 4'hF;  // Failed startup

    reg [31:0] initial_ssp, initial_pc;
    reg [7:0]  bus_timeout_counter;

    // Assign mock CPU outputs to testbench wires
    assign cpu_addr_w = mock_addr;
    assign size_w = mock_size;
    assign as_w = mock_as;
    assign wr_w = mock_rw;
    assign ds_w = mock_ds;
    assign rmc_w = mock_rmc;
    assign fc_w = mock_fc;
    assign cpu_dout_w = mock_dout;
    assign reset_out_w = mock_reset_out;

    //=================================================================
    // Initialize reset vector memory
    //=================================================================
    initial begin
        // Set up realistic reset vectors for Amiga
        reset_memory[0] = 32'h00080000;  // Initial SSP = 512KB
        reset_memory[1] = 32'h00F80000;  // Initial PC = ROM start
        reset_memory[2] = 32'h00000000;  // Unused
        reset_memory[3] = 32'h00000000;  // Unused
        reset_memory[4] = 32'h00000000;  // Unused
        reset_memory[5] = 32'h00000000;  // Unused
        reset_memory[6] = 32'h00000000;  // Unused
        reset_memory[7] = 32'h00000000;  // Unused
    end

    //=================================================================
    // Mock WF68K30L CPU Behavior
    //=================================================================
    always @(posedge clk) begin
        if (reset) begin
            // Reset state
            cpu_state <= CPU_RESET;
            mock_addr <= 32'h00000000;
            mock_size <= 2'b00;
            mock_as <= 1'b1;      // Inactive (active low)
            mock_rw <= 1'b1;      // Read
            mock_ds <= 1'b1;      // Inactive
            mock_rmc <= 1'b1;     // Inactive
            mock_fc <= 3'b110;    // Supervisor data
            mock_dout <= 32'h00000000;
            mock_reset_out <= 1'b0;  // Assert reset output
            initial_ssp <= 32'h00000000;
            initial_pc <= 32'h00000000;
            bus_timeout_counter <= 8'h00;
        end
        else begin
            case (cpu_state)
                CPU_RESET: begin
                    // Coming out of reset - start fetching reset vectors
                    mock_reset_out <= 1'b1;  // Release reset output
                    cpu_state <= CPU_FETCH_SSP_H;
                    bus_timeout_counter <= 8'h00;
                end

                CPU_FETCH_SSP_H: begin
                    // Fetch initial SSP (32-bit read from 0x000000)
                    mock_addr <= 32'h00000000;
                    mock_size <= 2'b11;      // 32-bit longword (CRITICAL TEST!)
                    mock_as <= 1'b0;         // Assert address strobe
                    mock_rw <= 1'b1;         // Read operation
                    mock_ds <= 1'b0;         // Assert data strobe
                    mock_fc <= 3'b110;       // Supervisor data access

                    // Wait for DSACK response
                    if (dsack_w != 2'b11) begin
                        // Got acknowledgment - capture data
                        initial_ssp <= cpu_din;
                        mock_as <= 1'b1;         // Deassert strobes
                        mock_ds <= 1'b1;
                        cpu_state <= CPU_FETCH_PC_H;
                        reset_vector_fetches <= reset_vector_fetches + 1;
                        $display("TIME %0t: SSP fetch successful: 0x%08X", $time, cpu_din);
                    end
                    else begin
                        bus_timeout_counter <= bus_timeout_counter + 1;
                        if (bus_timeout_counter > 100) begin
                            $display("TIME %0t: ERROR - SSP fetch timeout! DSACK=%b", $time, dsack_w);
                            cpu_state <= CPU_FAILED;
                            test_failed <= 1;
                        end
                    end
                end

                CPU_FETCH_PC_H: begin
                    // Fetch initial PC (32-bit read from 0x000004)
                    mock_addr <= 32'h00000004;
                    mock_size <= 2'b11;      // 32-bit longword
                    mock_as <= 1'b0;         // Assert address strobe
                    mock_rw <= 1'b1;         // Read operation
                    mock_ds <= 1'b0;         // Assert data strobe
                    mock_fc <= 3'b110;       // Supervisor data access

                    // Wait for DSACK response
                    if (dsack_w != 2'b11) begin
                        // Got acknowledgment - capture data
                        initial_pc <= cpu_din;
                        mock_as <= 1'b1;         // Deassert strobes
                        mock_ds <= 1'b1;
                        cpu_state <= CPU_RUNNING;
                        reset_vector_fetches <= reset_vector_fetches + 1;
                        $display("TIME %0t: PC fetch successful: 0x%08X", $time, cpu_din);
                        $display("TIME %0t: CPU STARTUP SUCCESSFUL! SSP=0x%08X PC=0x%08X",
                                $time, initial_ssp, initial_pc);
                        test_passed <= 1;
                    end
                    else begin
                        bus_timeout_counter <= bus_timeout_counter + 1;
                        if (bus_timeout_counter > 100) begin
                            $display("TIME %0t: ERROR - PC fetch timeout! DSACK=%b", $time, dsack_w);
                            cpu_state <= CPU_FAILED;
                            test_failed <= 1;
                        end
                    end
                end

                CPU_RUNNING: begin
                    // Successfully started - just idle
                    mock_as <= 1'b1;
                    mock_ds <= 1'b1;
                end

                CPU_FAILED: begin
                    // Startup failed - stay in failed state
                    mock_as <= 1'b1;
                    mock_ds <= 1'b1;
                end
            endcase
        end
    end

    //=================================================================
    // Memory Model with Realistic Timing
    //=================================================================
    always @(posedge clk) begin
        if (reset) begin
            dtack_active <= 0;
            mem_access_pending <= 0;
            access_delay_counter <= 0;
            cpu_din <= 32'h00000000;
        end
        else begin
            // Detect memory access request
            if (!as_w && !mem_access_pending) begin
                mem_access_pending <= 1;
                access_delay_counter <= 4;  // 4 cycle memory latency
                dtack_active <= 0;
                $display("TIME %0t: Memory access started - ADDR=0x%08X SIZE=%b",
                        $time, cpu_addr_w, size_w);
            end

            // Handle memory access timing
            if (mem_access_pending) begin
                if (access_delay_counter > 0) begin
                    access_delay_counter <= access_delay_counter - 1;
                end
                else begin
                    // Memory access ready - provide data and assert DTACK
                    if (cpu_addr_w >= 32'h00000000 && cpu_addr_w < 32'h00000020) begin
                        // Reset vector area
                        case (cpu_addr_w[4:2])
                            3'b000: cpu_din <= reset_memory[0];  // 0x000000-0x000003
                            3'b001: cpu_din <= reset_memory[1];  // 0x000004-0x000007
                            3'b010: cpu_din <= reset_memory[2];  // 0x000008-0x00000B
                            3'b011: cpu_din <= reset_memory[3];  // 0x00000C-0x00000F
                            3'b100: cpu_din <= reset_memory[4];  // 0x000010-0x000013
                            3'b101: cpu_din <= reset_memory[5];  // 0x000014-0x000017
                            3'b110: cpu_din <= reset_memory[6];  // 0x000018-0x00001B
                            3'b111: cpu_din <= reset_memory[7];  // 0x00001C-0x00001F
                        endcase
                        dtack_active <= 1;
                        $display("TIME %0t: Memory data ready - DATA=0x%08X DSACK=%b",
                                $time, cpu_din, dsack_w);
                    end
                    else begin
                        // Invalid address
                        cpu_din <= 32'hDEADBEEF;
                        dtack_active <= 1;
                        $display("TIME %0t: Invalid memory access - ADDR=0x%08X",
                                $time, cpu_addr_w);
                    end
                end
            end

            // Clear DTACK when AS is deasserted
            if (as_w) begin
                dtack_active <= 0;
                mem_access_pending <= 0;
                access_delay_counter <= 0;
            end
        end
    end

    //=================================================================
    // Test Control and Monitoring
    //=================================================================
    reg        prev_as_w;
    reg [1:0]  prev_size_w;
    reg [1:0]  prev_dsack_w;

    always @(posedge clk) begin
        cycle_count <= cycle_count + 1;

        // Display critical signals on changes
        if (!reset && cycle_count > 0) begin
            if (as_w != prev_as_w || size_w != prev_size_w || dsack_w != prev_dsack_w) begin
                $display("TIME %0t: BUS ACTIVITY - AS=%b SIZE=%b UDS=%b LDS=%b DSACK=%b LONGWORD=%b",
                        $time, as_w, size_w, uds_w, lds_w, dsack_w, longword_w);
            end
        end

        // Store previous values
        prev_as_w <= as_w;
        prev_size_w <= size_w;
        prev_dsack_w <= dsack_w;
    end

    //=================================================================
    // Main Test Sequence
    //=================================================================
    initial begin
        $display("=================================================================");
        $display("WF68K30L Power-On Sequence Test Starting...");
        $display("Testing the fixed SIZE signal interpretation and DSACK protocol");
        $display("=================================================================");

        // Generate VCD file for waveform analysis
        $dumpfile("wf68k30l_poweron.vcd");
        $dumpvars(0, test_wf68k30l_poweron);

        // Initial reset period
        reset = 1;
        #200;

        $display("TIME %0t: Releasing reset...", $time);
        reset = 0;

        // Wait for startup completion or timeout
        wait (test_passed || test_failed || cycle_count > 5000);

        #100; // Allow final transactions to complete

        // Test Results
        $display("=================================================================");
        $display("TEST RESULTS:");
        $display("=================================================================");
        if (test_passed) begin
            $display("PASS: WF68K30L startup sequence completed successfully!");
            $display("  - Reset vector fetches: %0d", reset_vector_fetches);
            $display("  - Initial SSP: 0x%08X", initial_ssp);
            $display("  - Initial PC: 0x%08X", initial_pc);
            $display("  - SIZE signal interpretation: WORKING");
            $display("  - DSACK protocol: WORKING");
        end
        else if (test_failed) begin
            $display("FAIL: WF68K30L startup sequence failed!");
            $display("  - CPU State: %0d", cpu_state);
            $display("  - Reset vector fetches: %0d", reset_vector_fetches);
            $display("  - Last DSACK value: %b", dsack_w);
            $display("  - Last SIZE value: %b", size_w);
            $display("  - DIAGNOSIS: Check SIZE signal interpretation and DSACK timing");
        end
        else begin
            $display("TIMEOUT: Test timed out after %0d cycles", cycle_count);
            $display("  - CPU State: %0d", cpu_state);
            $display("  - Possible infinite loop or protocol deadlock");
        end
        $display("=================================================================");

        $finish;
    end

    // Timeout safety
    initial begin
        #100000;  // 100µs timeout
        $display("EMERGENCY TIMEOUT: Test exceeded maximum time limit");
        $finish;
    end

endmodule

wf68k30l_poweron.vcd
$date
	Fri Sep 26 23:51:07 2025
$end
$version
	Icarus Verilog
$end
$timescale
	1ps
$end
$scope module test_wf68k30l_poweron $end
$var wire 32 ! cpu_dout_w [31:0] $end
$var wire 1 " ds_w $end
$var wire 3 # fc_w [2:0] $end
$var wire 1 $ reset_out_w $end
$var wire 1 % rmc_w $end
$var wire 2 & size_w [1:0] $end
$var wire 1 ' wr_w $end
$var wire 1 ( uds_w $end
$var wire 1 ) longword_w $end
$var wire 1 * lds_w $end
$var wire 2 + dsack_w [1:0] $end
$var wire 2 , cpustate_w [1:0] $end
$var wire 32 - cpu_addr_w [31:0] $end
$var wire 2 . byte_lanes [1:0] $end
$var wire 1 / as_w $end
$var parameter 4 0 CPU_FAILED $end
$var parameter 4 1 CPU_FETCH_PC_H $end
$var parameter 4 2 CPU_FETCH_PC_L $end
$var parameter 4 3 CPU_FETCH_SSP_H $end
$var parameter 4 4 CPU_FETCH_SSP_L $end
$var parameter 4 5 CPU_RESET $end
$var parameter 4 6 CPU_RUNNING $end
$var reg 4 7 access_delay_counter [3:0] $end
$var reg 8 8 bus_timeout_counter [7:0] $end
$var reg 3 9 cachecfg [2:0] $end
$var reg 3 : chip_ipl [2:0] $end
$var reg 1 ; clk $end
$var reg 32 < cpu_din [31:0] $end
$var reg 4 = cpu_state [3:0] $end
$var reg 3 > cpucfg [2:0] $end
$var reg 1 ? dtack_active $end
$var reg 32 @ initial_pc [31:0] $end
$var reg 32 A initial_ssp [31:0] $end
$var reg 1 B mem_access_pending $end
$var reg 32 C mock_addr [31:0] $end
$var reg 1 / mock_as $end
$var reg 32 D mock_dout [31:0] $end
$var reg 1 E mock_ds $end
$var reg 3 F mock_fc [2:0] $end
$var reg 1 G mock_reset_out $end
$var reg 1 H mock_rmc $end
$var reg 1 ' mock_rw $end
$var reg 2 I mock_size [1:0] $end
$var reg 1 J prev_as_w $end
$var reg 2 K prev_dsack_w [1:0] $end
$var reg 2 L prev_size_w [1:0] $end
$var reg 1 M reset $end
$var reg 1 N test_failed $end
$var reg 1 O test_passed $end
$var integer 32 P cycle_count [31:0] $end
$var integer 32 Q reset_vector_fetches [31:0] $end
$upscope $end
$enddefinitions $end
$comment Show the parameter values. $end
$dumpall
b101 6
b0 5
b10 4
b1 3
b100 2
b11 1
b1111 0
$end
#0
$dumpvars
b0 Q
b0 P
0O
0N
1M
bx L
bx K
xJ
bx I
xH
xG
bx F
xE
bx D
bx C
0B
bx A
bx @
0?
b100 >
bx =
bx <
0;
b111 :
b0 9
bx 8
b0 7
x/
bx .
bx -
bx ,
b11 +
x*
x)
x(
x'
bx &
x%
x$
bx #
x"
bx !
$end
#10000
0(
1*
b1 ,
b0 .
b0 8
b0 @
b0 A
0$
0G
b0 !
b0 D
b110 #
b110 F
1%
1H
1"
1E
1'
1/
0)
b0 &
b0 I
b0 -
b0 C
b0 =
b0 <
b11 K
b1 P
1;
#20000
0;
#30000
b0 L
1J
b10 P
1;
#40000
0;
#50000
b11 P
1;
#60000
0;
#70000
b100 P
1;
#80000
0;
#90000
b101 P
1;
#100000
0;
#110000
b110 P
1;
#120000
0;
#130000
b111 P
1;
#140000
0;
#150000
b1000 P
1;
#160000
0;
#170000
b1001 P
1;
#180000
0;
#190000
b1010 P
1;
#200000
0;
0M
#210000
b1 =
1$
1G
b1011 P
1;
#220000
0;
#230000
0*
b10 ,
0(
b1100 P
b1 8
0"
0E
0/
1)
b11 &
b11 I
1;
#240000
0;
#250000
b10 8
b100 7
1B
b11 L
0J
b1101 P
1;
#260000
0;
#270000
b1110 P
b11 7
b11 8
1;
#280000
0;
#290000
b100 8
b10 7
b1111 P
1;
#300000
0;
#310000
b10000 P
b1 7
b101 8
1;
#320000
0;
#330000
b110 8
b0 7
b10001 P
1;
#340000
0;
#350000
b0 +
b10010 P
1?
b10000000000000000000 <
b111 8
1;
#360000
0;
#370000
b1 ,
b1 Q
b11 =
1"
1E
1/
b10000000000000000000 A
b0 K
b10011 P
1;
#380000
0;
#390000
b11 +
1J
b10100 P
0B
0?
1O
b10 Q
b101 =
b10000000000000000000 @
1"
1E
1/
b100 -
b100 C
1;
#400000
0;
#410000
b11 K
b10101 P
1;
#420000
0;
#430000
b10110 P
1;
#440000
0;
#450000
b10111 P
1;
#460000
0;
#470000
b11000 P
1;
#480000
0;
#490000
b11001 P
1;
