test_wf68k30l_broken.v
// WF68K30L Power-On Sequence Testbench - BROKEN VERSION
// Demonstrates the startup failure with the original incorrect SIZE signal interpretation
// This shows what happens with the buggy code before my fixes

`timescale 1ns/1ps

module test_wf68k30l_broken();

    // Basic test signals
    reg clk = 0;
    reg reset = 1;
    reg [2:0] cpucfg = 3'b100;     // WF68K30L selected (cpucfg[2] = 1)
    reg [2:0] cachecfg = 3'b000;   // No cache optimizations for testing
    reg [2:0] chip_ipl = 3'b111;   // No interrupts during startup

    // Clock generation - 50MHz system clock
    always #10 clk = ~clk;

    // Memory model for reset vector area (0x00000000 - 0x0000001F)
    reg [31:0] reset_memory [0:7];

    // CPU interface signals (from cpu_wrapper.v)
    wire [31:0] cpu_addr_w;
    wire [31:0] cpu_dout_w;
    reg  [31:0] cpu_din;
    wire [1:0]  size_w;
    wire        as_w;
    wire        wr_w;
    wire        ds_w;
    wire        rmc_w;
    wire [2:0]  fc_w;
    wire        reset_out_w;

    // Bus protocol signals
    wire [1:0]  dsack_w;
    wire        uds_w;
    wire        lds_w;
    wire        longword_w;
    wire [1:0]  cpustate_w;

    // Memory access control
    reg         dtack_active = 0;
    reg         mem_access_pending = 0;
    reg [3:0]   access_delay_counter = 0;

    // Test control
    integer     cycle_count = 0;
    integer     reset_vector_fetches = 0;
    reg         test_passed = 0;
    reg         test_failed = 0;

    //=================================================================
    // BROKEN WF68K30L bus conversion logic (ORIGINAL BUGGY CODE!)
    //=================================================================

    // BROKEN DSACK generation for WF68K30L (incorrect SIZE handling)
    // This was the original broken formula that caused startup failures
    assign dsack_w = dtack_active ? {size_w[1] | size_w[0], size_w[1] | ~size_w[0]} : 2'b11;

    // BROKEN SIZE to UDS/LDS conversion (incorrect longword detection)
    wire [1:0] byte_lanes = cpu_addr_w[1:0];
    assign uds_w = (size_w == 2'b00) ? ~(byte_lanes == 2'b00 || byte_lanes == 2'b01) :  // Byte: UDS for upper bytes
                   (size_w == 2'b01) ? ~cpu_addr_w[1] :                                   // Word: UDS based on alignment
                   (size_w == 2'b10) ? 1'b0 :                                            // BROKEN: Should be 2'b11!
                   1'b1;                                                                 // Reserved

    assign lds_w = (size_w == 2'b00) ? ~(byte_lanes == 2'b10 || byte_lanes == 2'b11) :  // Byte: LDS for lower bytes
                   (size_w == 2'b01) ? ~cpu_addr_w[1] :                                   // Word: LDS based on alignment
                   (size_w == 2'b10) ? 1'b0 :                                            // BROKEN: Should be 2'b11!
                   1'b1;                                                                 // Reserved

    // Map WF68K30L bus state to cpustate (invert AS since WF68K30L uses active low)
    assign cpustate_w = as_w ? 2'b01 : (~wr_w ? 2'b11 : 2'b10);
    assign longword_w = (size_w == 2'b10);  // BROKEN: Should be 2'b11!

    //=================================================================
    // Mock WF68K30L CPU Core - Behavioral Model
    //=================================================================

    reg [31:0] mock_addr;
    reg [1:0]  mock_size;
    reg        mock_as;
    reg        mock_rw;
    reg        mock_ds;
    reg        mock_rmc;
    reg [2:0]  mock_fc;
    reg [31:0] mock_dout;
    reg        mock_reset_out;

    // State machine for MC68030 startup sequence
    reg [3:0] cpu_state;
    parameter
        CPU_RESET       = 4'h0,
        CPU_FETCH_SSP_H = 4'h1,  // Fetch high word of initial SSP from 0x000000
        CPU_FETCH_SSP_L = 4'h2,  // Fetch low word of initial SSP from 0x000002
        CPU_FETCH_PC_H  = 4'h3,  // Fetch high word of initial PC from 0x000004
        CPU_FETCH_PC_L  = 4'h4,  // Fetch low word of initial PC from 0x000006
        CPU_RUNNING     = 4'h5,  // Normal operation
        CPU_FAILED      = 4'hF;  // Failed startup

    reg [31:0] initial_ssp, initial_pc;
    reg [7:0]  bus_timeout_counter;

    // Assign mock CPU outputs to testbench wires
    assign cpu_addr_w = mock_addr;
    assign size_w = mock_size;
    assign as_w = mock_as;
    assign wr_w = mock_rw;
    assign ds_w = mock_ds;
    assign rmc_w = mock_rmc;
    assign fc_w = mock_fc;
    assign cpu_dout_w = mock_dout;
    assign reset_out_w = mock_reset_out;

    //=================================================================
    // Initialize reset vector memory
    //=================================================================
    initial begin
        // Set up realistic reset vectors for Amiga
        reset_memory[0] = 32'h00080000;  // Initial SSP = 512KB
        reset_memory[1] = 32'h00F80000;  // Initial PC = ROM start
        reset_memory[2] = 32'h00000000;  // Unused
        reset_memory[3] = 32'h00000000;  // Unused
        reset_memory[4] = 32'h00000000;  // Unused
        reset_memory[5] = 32'h00000000;  // Unused
        reset_memory[6] = 32'h00000000;  // Unused
        reset_memory[7] = 32'h00000000;  // Unused
    end

    //=================================================================
    // Mock WF68K30L CPU Behavior
    //=================================================================
    always @(posedge clk) begin
        if (reset) begin
            // Reset state
            cpu_state <= CPU_RESET;
            mock_addr <= 32'h00000000;
            mock_size <= 2'b00;
            mock_as <= 1'b1;      // Inactive (active low)
            mock_rw <= 1'b1;      // Read
            mock_ds <= 1'b1;      // Inactive
            mock_rmc <= 1'b1;     // Inactive
            mock_fc <= 3'b110;    // Supervisor data
            mock_dout <= 32'h00000000;
            mock_reset_out <= 1'b0;  // Assert reset output
            initial_ssp <= 32'h00000000;
            initial_pc <= 32'h00000000;
            bus_timeout_counter <= 8'h00;
        end
        else begin
            case (cpu_state)
                CPU_RESET: begin
                    // Coming out of reset - start fetching reset vectors
                    mock_reset_out <= 1'b1;  // Release reset output
                    cpu_state <= CPU_FETCH_SSP_H;
                    bus_timeout_counter <= 8'h00;
                end

                CPU_FETCH_SSP_H: begin
                    // Fetch initial SSP (32-bit read from 0x000000)
                    mock_addr <= 32'h00000000;
                    mock_size <= 2'b11;      // 32-bit longword (WILL FAIL WITH BROKEN CODE!)
                    mock_as <= 1'b0;         // Assert address strobe
                    mock_rw <= 1'b1;         // Read operation
                    mock_ds <= 1'b0;         // Assert data strobe
                    mock_fc <= 3'b110;       // Supervisor data access

                    // Wait for DSACK response
                    if (dsack_w != 2'b11) begin
                        // Got acknowledgment - capture data
                        initial_ssp <= cpu_din;
                        mock_as <= 1'b1;         // Deassert strobes
                        mock_ds <= 1'b1;
                        cpu_state <= CPU_FETCH_PC_H;
                        reset_vector_fetches <= reset_vector_fetches + 1;
                        $display("TIME %0t: SSP fetch successful: 0x%08X", $time, cpu_din);
                    end
                    else begin
                        bus_timeout_counter <= bus_timeout_counter + 1;
                        if (bus_timeout_counter > 100) begin
                            $display("TIME %0t: ERROR - SSP fetch timeout! DSACK=%b SIZE=%b", $time, dsack_w, size_w);
                            $display("TIME %0t: BROKEN SIZE INTERPRETATION - SIZE=11 should generate DSACK=00 but got DSACK=%b", $time, dsack_w);
                            cpu_state <= CPU_FAILED;
                            test_failed <= 1;
                        end
                    end
                end

                CPU_FETCH_PC_H: begin
                    // This will never be reached with broken code
                    cpu_state <= CPU_FAILED;
                    test_failed <= 1;
                end

                CPU_RUNNING: begin
                    // This will never be reached with broken code
                    mock_as <= 1'b1;
                    mock_ds <= 1'b1;
                end

                CPU_FAILED: begin
                    // Startup failed - stay in failed state
                    mock_as <= 1'b1;
                    mock_ds <= 1'b1;
                end
            endcase
        end
    end

    //=================================================================
    // Memory Model with Realistic Timing
    //=================================================================
    always @(posedge clk) begin
        if (reset) begin
            dtack_active <= 0;
            mem_access_pending <= 0;
            access_delay_counter <= 0;
            cpu_din <= 32'h00000000;
        end
        else begin
            // Detect memory access request
            if (!as_w && !mem_access_pending) begin
                mem_access_pending <= 1;
                access_delay_counter <= 4;  // 4 cycle memory latency
                dtack_active <= 0;
                $display("TIME %0t: Memory access started - ADDR=0x%08X SIZE=%b", $time, cpu_addr_w, size_w);
            end

            // Handle memory access timing
            if (mem_access_pending) begin
                if (access_delay_counter > 0) begin
                    access_delay_counter <= access_delay_counter - 1;
                end
                else begin
                    // Memory access ready - provide data and assert DTACK
                    if (cpu_addr_w >= 32'h00000000 && cpu_addr_w < 32'h00000020) begin
                        // Reset vector area
                        case (cpu_addr_w[4:2])
                            3'b000: cpu_din <= reset_memory[0];  // 0x000000-0x000003
                            3'b001: cpu_din <= reset_memory[1];  // 0x000004-0x000007
                            3'b010: cpu_din <= reset_memory[2];  // 0x000008-0x00000B
                            3'b011: cpu_din <= reset_memory[3];  // 0x00000C-0x00000F
                            3'b100: cpu_din <= reset_memory[4];  // 0x000010-0x000013
                            3'b101: cpu_din <= reset_memory[5];  // 0x000014-0x000017
                            3'b110: cpu_din <= reset_memory[6];  // 0x000018-0x00001B
                            3'b111: cpu_din <= reset_memory[7];  // 0x00001C-0x00001F
                        endcase
                        dtack_active <= 1;
                        $display("TIME %0t: Memory data ready - DATA=0x%08X DSACK=%b (BROKEN!)", $time, cpu_din, dsack_w);
                    end
                    else begin
                        // Invalid address
                        cpu_din <= 32'hDEADBEEF;
                        dtack_active <= 1;
                        $display("TIME %0t: Invalid memory access - ADDR=0x%08X", $time, cpu_addr_w);
                    end
                end
            end

            // Clear DTACK when AS is deasserted
            if (as_w) begin
                dtack_active <= 0;
                mem_access_pending <= 0;
                access_delay_counter <= 0;
            end
        end
    end

    //=================================================================
    // Test Control and Monitoring
    //=================================================================
    reg        prev_as_w;
    reg [1:0]  prev_size_w;
    reg [1:0]  prev_dsack_w;

    always @(posedge clk) begin
        cycle_count <= cycle_count + 1;

        // Display critical signals on changes
        if (!reset && cycle_count > 0) begin
            if (as_w != prev_as_w || size_w != prev_size_w || dsack_w != prev_dsack_w) begin
                $display("TIME %0t: BUS ACTIVITY - AS=%b SIZE=%b UDS=%b LDS=%b DSACK=%b LONGWORD=%b (BROKEN!)",
                        $time, as_w, size_w, uds_w, lds_w, dsack_w, longword_w);
            end
        end

        // Store previous values
        prev_as_w <= as_w;
        prev_size_w <= size_w;
        prev_dsack_w <= dsack_w;
    end

    //=================================================================
    // Main Test Sequence
    //=================================================================
    initial begin
        $display("=================================================================");
        $display("WF68K30L Power-On Sequence Test - BROKEN VERSION");
        $display("Demonstrating the startup failure with incorrect SIZE interpretation");
        $display("=================================================================");

        // Generate VCD file for waveform analysis
        $dumpfile("wf68k30l_broken.vcd");
        $dumpvars(0, test_wf68k30l_broken);

        // Initial reset period
        reset = 1;
        #200;

        $display("TIME %0t: Releasing reset...", $time);
        reset = 0;

        // Wait for startup completion or timeout
        wait (test_passed || test_failed || cycle_count > 5000);

        #100; // Allow final transactions to complete

        // Test Results
        $display("=================================================================");
        $display("TEST RESULTS - BROKEN VERSION:");
        $display("=================================================================");
        if (test_passed) begin
            $display("UNEXPECTED: Test passed - this should have failed!");
        end
        else if (test_failed) begin
            $display("EXPECTED FAILURE: WF68K30L startup failed as expected!");
            $display("  - CPU State: %0d", cpu_state);
            $display("  - Reset vector fetches: %0d", reset_vector_fetches);
            $display("  - Last DSACK value: %b", dsack_w);
            $display("  - Last SIZE value: %b", size_w);
            $display("  - ROOT CAUSE: SIZE=11 (longword) incorrectly treated as SIZE=10 (3-byte)");
            $display("  - EXPLANATION: The broken formula generates wrong DSACK for 32-bit transfers");
            $display("  - SOLUTION: Fix SIZE signal interpretation to use 2'b11 for longword detection");
        end
        else begin
            $display("TIMEOUT: Test timed out after %0d cycles", cycle_count);
            $display("  - CPU State: %0d", cpu_state);
            $display("  - This indicates a protocol deadlock");
        end
        $display("=================================================================");

        $finish;
    end

    // Timeout safety
    initial begin
        #100000;  // 100µs timeout
        $display("EMERGENCY TIMEOUT: Test exceeded maximum time limit");
        $finish;
    end

endmodule

wf68k30l_broken.vcd
$date
	Mon Oct  6 23:03:15 2025
$end
$version
	Icarus Verilog
$end
$timescale
	1ps
$end
$scope module test_wf68k30l_broken $end
$var wire 32 ! cpu_dout_w [31:0] $end
$var wire 1 " ds_w $end
$var wire 3 # fc_w [2:0] $end
$var wire 1 $ reset_out_w $end
$var wire 1 % rmc_w $end
$var wire 2 & size_w [1:0] $end
$var wire 1 ' wr_w $end
$var wire 1 ( uds_w $end
$var wire 1 ) longword_w $end
$var wire 1 * lds_w $end
$var wire 2 + dsack_w [1:0] $end
$var wire 2 , cpustate_w [1:0] $end
$var wire 32 - cpu_addr_w [31:0] $end
$var wire 2 . byte_lanes [1:0] $end
$var wire 1 / as_w $end
$var parameter 4 0 CPU_FAILED $end
$var parameter 4 1 CPU_FETCH_PC_H $end
$var parameter 4 2 CPU_FETCH_PC_L $end
$var parameter 4 3 CPU_FETCH_SSP_H $end
$var parameter 4 4 CPU_FETCH_SSP_L $end
$var parameter 4 5 CPU_RESET $end
$var parameter 4 6 CPU_RUNNING $end
$var reg 4 7 access_delay_counter [3:0] $end
$var reg 8 8 bus_timeout_counter [7:0] $end
$var reg 3 9 cachecfg [2:0] $end
$var reg 3 : chip_ipl [2:0] $end
$var reg 1 ; clk $end
$var reg 32 < cpu_din [31:0] $end
$var reg 4 = cpu_state [3:0] $end
$var reg 3 > cpucfg [2:0] $end
$var reg 1 ? dtack_active $end
$var reg 32 @ initial_pc [31:0] $end
$var reg 32 A initial_ssp [31:0] $end
$var reg 1 B mem_access_pending $end
$var reg 32 C mock_addr [31:0] $end
$var reg 1 / mock_as $end
$var reg 32 D mock_dout [31:0] $end
$var reg 1 E mock_ds $end
$var reg 3 F mock_fc [2:0] $end
$var reg 1 G mock_reset_out $end
$var reg 1 H mock_rmc $end
$var reg 1 ' mock_rw $end
$var reg 2 I mock_size [1:0] $end
$var reg 1 J prev_as_w $end
$var reg 2 K prev_dsack_w [1:0] $end
$var reg 2 L prev_size_w [1:0] $end
$var reg 1 M reset $end
$var reg 1 N test_failed $end
$var reg 1 O test_passed $end
$var integer 32 P cycle_count [31:0] $end
$var integer 32 Q reset_vector_fetches [31:0] $end
$upscope $end
$enddefinitions $end
$comment Show the parameter values. $end
$dumpall
b101 6
b0 5
b10 4
b1 3
b100 2
b11 1
b1111 0
$end
#0
$dumpvars
b0 Q
b0 P
0O
0N
1M
bx L
bx K
xJ
bx I
xH
xG
bx F
xE
bx D
bx C
0B
bx A
bx @
0?
b100 >
bx =
bx <
0;
b111 :
b0 9
bx 8
b0 7
x/
bx .
bx -
bx ,
b11 +
x*
x)
x(
x'
bx &
x%
x$
bx #
x"
bx !
$end
#10000
0(
1*
b1 ,
b0 .
b0 8
b0 @
b0 A
0$
0G
b0 !
b0 D
b110 #
b110 F
1%
1H
1"
1E
1'
1/
0)
b0 &
b0 I
b0 -
b0 C
b0 =
b0 <
b11 K
b1 P
1;
#20000
0;
#30000
b0 L
1J
b10 P
1;
#40000
0;
#50000
b11 P
1;
#60000
0;
#70000
b100 P
1;
#80000
0;
#90000
b101 P
1;
#100000
0;
#110000
b110 P
1;
#120000
0;
#130000
b111 P
1;
#140000
0;
#150000
b1000 P
1;
#160000
0;
#170000
b1001 P
1;
#180000
0;
#190000
b1010 P
1;
#200000
0;
0M
#210000
b1 =
1$
1G
b1011 P
1;
#220000
0;
#230000
b10 ,
1(
b1100 P
b1 8
0"
0E
0/
b11 &
b11 I
1;
#240000
0;
#250000
b10 8
b100 7
1B
b11 L
0J
b1101 P
1;
#260000
0;
#270000
b1110 P
b11 7
b11 8
1;
#280000
0;
#290000
b100 8
b10 7
b1111 P
1;
#300000
0;
#310000
b10000 P
b1 7
b101 8
1;
#320000
0;
#330000
b110 8
b0 7
b10001 P
1;
#340000
0;
#350000
b10010 P
1?
b10000000000000000000 <
b111 8
1;
#360000
0;
#370000
b1000 8
b10011 P
1;
#380000
0;
#390000
b10100 P
b1001 8
1;
#400000
0;
#410000
b1010 8
b10101 P
1;
#420000
0;
#430000
b10110 P
b1011 8
1;
#440000
0;
#450000
b1100 8
b10111 P
1;
#460000
0;
#470000
b11000 P
b1101 8
1;
#480000
0;
#490000
b1110 8
b11001 P
1;
#500000
0;
#510000
b11010 P
b1111 8
1;
#520000
0;
#530000
b10000 8
b11011 P
1;
#540000
0;
#550000
b11100 P
b10001 8
1;
#560000
0;
#570000
b10010 8
b11101 P
1;
#580000
0;
#590000
b11110 P
b10011 8
1;
#600000
0;
#610000
b10100 8
b11111 P
1;
#620000
0;
#630000
b100000 P
b10101 8
1;
#640000
0;
#650000
b10110 8
b100001 P
1;
#660000
0;
#670000
b100010 P
b10111 8
1;
#680000
0;
#690000
b11000 8
b100011 P
1;
#700000
0;
#710000
b100100 P
b11001 8
1;
#720000
0;
#730000
b11010 8
b100101 P
1;
#740000
0;
#750000
b100110 P
b11011 8
1;
#760000
0;
#770000
b11100 8
b100111 P
1;
#780000
0;
#790000
b101000 P
b11101 8
1;
#800000
0;
#810000
b11110 8
b101001 P
1;
#820000
0;
#830000
b101010 P
b11111 8
1;
#840000
0;
#850000
b100000 8
b101011 P
1;
#860000
0;
#870000
b101100 P
b100001 8
1;
#880000
0;
#890000
b100010 8
b101101 P
1;
#900000
0;
#910000
b101110 P
b100011 8
1;
#920000
0;
#930000
b100100 8
b101111 P
1;
#940000
0;
#950000
b110000 P
b100101 8
1;
#960000
0;
#970000
b100110 8
b110001 P
1;
#980000
0;
#990000
b110010 P
b100111 8
1;
#1000000
0;
#1010000
b101000 8
b110011 P
1;
#1020000
0;
#1030000
b110100 P
b101001 8
1;
#1040000
0;
#1050000
b101010 8
b110101 P
1;
#1060000
0;
#1070000
b110110 P
b101011 8
1;
#1080000
0;
#1090000
b101100 8
b110111 P
1;
#1100000
0;
#1110000
b111000 P
b101101 8
1;
#1120000
0;
#1130000
b101110 8
b111001 P
1;
#1140000
0;
#1150000
b111010 P
b101111 8
1;
#1160000
0;
#1170000
b110000 8
b111011 P
1;
#1180000
0;
#1190000
b111100 P
b110001 8
1;
#1200000
0;
#1210000
b110010 8
b111101 P
1;
#1220000
0;
#1230000
b111110 P
b110011 8
1;
#1240000
0;
#1250000
b110100 8
b111111 P
1;
#1260000
0;
#1270000
b1000000 P
b110101 8
1;
#1280000
0;
#1290000
b110110 8
b1000001 P
1;
#1300000
0;
#1310000
b1000010 P
b110111 8
1;
#1320000
0;
#1330000
b111000 8
b1000011 P
1;
#1340000
0;
#1350000
b1000100 P
b111001 8
1;
#1360000
0;
#1370000
b111010 8
b1000101 P
1;
#1380000
0;
#1390000
b1000110 P
b111011 8
1;
#1400000
0;
#1410000
b111100 8
b1000111 P
1;
#1420000
0;
#1430000
b1001000 P
b111101 8
1;
#1440000
0;
#1450000
b111110 8
b1001001 P
1;
#1460000
0;
#1470000
b1001010 P
b111111 8
1;
#1480000
0;
#1490000
b1000000 8
b1001011 P
1;
#1500000
0;
#1510000
b1001100 P
b1000001 8
1;
#1520000
0;
#1530000
b1000010 8
b1001101 P
1;
#1540000
0;
#1550000
b1001110 P
b1000011 8
1;
#1560000
0;
#1570000
b1000100 8
b1001111 P
1;
#1580000
0;
#1590000
b1010000 P
b1000101 8
1;
#1600000
0;
#1610000
b1000110 8
b1010001 P
1;
#1620000
0;
#1630000
b1010010 P
b1000111 8
1;
#1640000
0;
#1650000
b1001000 8
b1010011 P
1;
#1660000
0;
#1670000
b1010100 P
b1001001 8
1;
#1680000
0;
#1690000
b1001010 8
b1010101 P
1;
#1700000
0;
#1710000
b1010110 P
b1001011 8
1;
#1720000
0;
#1730000
b1001100 8
b1010111 P
1;
#1740000
0;
#1750000
b1011000 P
b1001101 8
1;
#1760000
0;
#1770000
b1001110 8
b1011001 P
1;
#1780000
0;
#1790000
b1011010 P
b1001111 8
1;
#1800000
0;
#1810000
b1010000 8
b1011011 P
1;
#1820000
0;
#1830000
b1011100 P
b1010001 8
1;
#1840000
0;
#1850000
b1010010 8
b1011101 P
1;
#1860000
0;
#1870000
b1011110 P
b1010011 8
1;
#1880000
0;
#1890000
b1010100 8
b1011111 P
1;
#1900000
0;
#1910000
b1100000 P
b1010101 8
1;
#1920000
0;
#1930000
b1010110 8
b1100001 P
1;
#1940000
0;
#1950000
b1100010 P
b1010111 8
1;
#1960000
0;
#1970000
b1011000 8
b1100011 P
1;
#1980000
0;
#1990000
b1100100 P
b1011001 8
1;
#2000000
0;
#2010000
b1011010 8
b1100101 P
1;
#2020000
0;
#2030000
b1100110 P
b1011011 8
1;
#2040000
0;
#2050000
b1011100 8
b1100111 P
1;
#2060000
0;
#2070000
b1101000 P
b1011101 8
1;
#2080000
0;
#2090000
b1011110 8
b1101001 P
1;
#2100000
0;
#2110000
b1101010 P
b1011111 8
1;
#2120000
0;
#2130000
b1100000 8
b1101011 P
1;
#2140000
0;
#2150000
b1101100 P
b1100001 8
1;
#2160000
0;
#2170000
b1100010 8
b1101101 P
1;
#2180000
0;
#2190000
b1101110 P
b1100011 8
1;
#2200000
0;
#2210000
b1100100 8
b1101111 P
1;
#2220000
0;
#2230000
b1110000 P
b1100101 8
1;
#2240000
0;
#2250000
1N
b1111 =
b1100110 8
b1110001 P
1;
#2260000
0;
#2270000
b1 ,
b1110010 P
1"
1E
1/
1;
#2280000
0;
#2290000
0B
0?
1J
b1110011 P
1;
#2300000
0;
#2310000
b1110100 P
1;
#2320000
0;
#2330000
b1110101 P
1;
#2340000
0;
#2350000
b1110110 P
1;
